<?xml version="1.0" encoding="UTF-8"?>
<con:soapui-project id="28bf13fe-2912-47b1-a975-9a537a784e20" activeEnvironment="Default" name="Potato Service" resourceRoot="" soapui-version="5.5.0" abortOnError="false" runType="SEQUENTIAL" xmlns:con="http://eviware.com/soapui/config"><con:settings/><con:interface xsi:type="con:WsdlInterface" id="a4943e09-8884-46d9-a1cc-72170b5faa33" wsaVersion="NONE" name="PotatoServiceImplPortBinding" type="wsdl" bindingName="{http://service.soap.william.me/}PotatoServiceImplPortBinding" soapVersion="1_1" anonymous="optional" definition="file:/home/william/IdeaProjects/soap-web-service/src/main/resources/potato-service.wsdl" xmlns:xsi="http://www.w3.org/2001/XMLSchema-instance"><con:settings/><con:definitionCache type="TEXT" rootPart="file:/home/william/IdeaProjects/soap-web-service/src/main/resources/potato-service.wsdl"><con:part><con:url>file:/home/william/IdeaProjects/soap-web-service/src/main/resources/potato-service.wsdl</con:url><con:content><![CDATA[<!--Published by JAX-WS RI at http://jax-ws.dev.java.net. RI's version is JAX-WS RI 2.2.7-b01  svn-revision#.-->
<!--Generated by JAX-WS RI at http://jax-ws.dev.java.net. RI's version is JAX-WS RI 2.2.7-b01  svn-revision#.-->
<definitions targetNamespace="http://service.soap.william.me/" name="PotatoServiceImplService" xmlns:wsu="http://docs.oasis-open.org/wss/2004/01/oasis-200401-wss-wssecurity-utility-1.0.xsd" xmlns:wsp="http://www.w3.org/ns/ws-policy" xmlns:wsp1_2="http://schemas.xmlsoap.org/ws/2004/09/policy" xmlns:wsam="http://www.w3.org/2007/05/addressing/metadata" xmlns:soap="http://schemas.xmlsoap.org/wsdl/soap/" xmlns:tns="http://service.soap.william.me/" xmlns:xsd="http://www.w3.org/2001/XMLSchema" xmlns="http://schemas.xmlsoap.org/wsdl/">
  <types>
    <xsd:schema>
      <xsd:import namespace="http://service.soap.william.me/" schemaLocation="http://localhost:8000/services/Potato?xsd=1"/>
    </xsd:schema>
  </types>
  <message name="addPotato">
    <part name="arg0" type="tns:potato"/>
  </message>
  <message name="addPotatoResponse">
    <part name="return" type="xsd:boolean"/>
  </message>
  <message name="deletePotato">
    <part name="arg0" type="xsd:int"/>
  </message>
  <message name="deletePotatoResponse">
    <part name="return" type="xsd:boolean"/>
  </message>
  <message name="getPotato">
    <part name="arg0" type="xsd:int"/>
  </message>
  <message name="getPotatoResponse">
    <part name="return" type="tns:potato"/>
  </message>
  <message name="getAllPotatoes"/>
  <message name="getAllPotatoesResponse">
    <part name="return" type="tns:potatoArray"/>
  </message>
  <portType name="PotatoService">
    <operation name="addPotato">
      <input wsam:Action="http://service.soap.william.me/PotatoService/addPotatoRequest" message="tns:addPotato"/>
      <output wsam:Action="http://service.soap.william.me/PotatoService/addPotatoResponse" message="tns:addPotatoResponse"/>
    </operation>
    <operation name="deletePotato">
      <input wsam:Action="http://service.soap.william.me/PotatoService/deletePotatoRequest" message="tns:deletePotato"/>
      <output wsam:Action="http://service.soap.william.me/PotatoService/deletePotatoResponse" message="tns:deletePotatoResponse"/>
    </operation>
    <operation name="getPotato">
      <input wsam:Action="http://service.soap.william.me/PotatoService/getPotatoRequest" message="tns:getPotato"/>
      <output wsam:Action="http://service.soap.william.me/PotatoService/getPotatoResponse" message="tns:getPotatoResponse"/>
    </operation>
    <operation name="getAllPotatoes">
      <input wsam:Action="http://service.soap.william.me/PotatoService/getAllPotatoesRequest" message="tns:getAllPotatoes"/>
      <output wsam:Action="http://service.soap.william.me/PotatoService/getAllPotatoesResponse" message="tns:getAllPotatoesResponse"/>
    </operation>
  </portType>
  <binding name="PotatoServiceImplPortBinding" type="tns:PotatoService">
    <soap:binding transport="http://schemas.xmlsoap.org/soap/http" style="rpc"/>
    <operation name="addPotato">
      <soap:operation soapAction=""/>
      <input>
        <soap:body use="literal" namespace="http://service.soap.william.me/"/>
      </input>
      <output>
        <soap:body use="literal" namespace="http://service.soap.william.me/"/>
      </output>
    </operation>
    <operation name="deletePotato">
      <soap:operation soapAction=""/>
      <input>
        <soap:body use="literal" namespace="http://service.soap.william.me/"/>
      </input>
      <output>
        <soap:body use="literal" namespace="http://service.soap.william.me/"/>
      </output>
    </operation>
    <operation name="getPotato">
      <soap:operation soapAction=""/>
      <input>
        <soap:body use="literal" namespace="http://service.soap.william.me/"/>
      </input>
      <output>
        <soap:body use="literal" namespace="http://service.soap.william.me/"/>
      </output>
    </operation>
    <operation name="getAllPotatoes">
      <soap:operation soapAction=""/>
      <input>
        <soap:body use="literal" namespace="http://service.soap.william.me/"/>
      </input>
      <output>
        <soap:body use="literal" namespace="http://service.soap.william.me/"/>
      </output>
    </operation>
  </binding>
  <service name="PotatoServiceImplService">
    <port name="PotatoServiceImplPort" binding="tns:PotatoServiceImplPortBinding">
      <soap:address location="http://localhost:8000/services/Potato"/>
    </port>
  </service>
</definitions>]]></con:content><con:type>http://schemas.xmlsoap.org/wsdl/</con:type></con:part><con:part><con:url>http://localhost:8000/services/Potato?xsd=1</con:url><con:content><![CDATA[<!--Published by JAX-WS RI at http://jax-ws.dev.java.net. RI's version is JAX-WS RI 2.2.7-b01  svn-revision#.-->
<xs:schema version="1.0" targetNamespace="http://service.soap.william.me/" xmlns:tns="http://service.soap.william.me/" xmlns:xs="http://www.w3.org/2001/XMLSchema">
  <xs:complexType name="potato">
    <xs:sequence>
      <xs:element name="breed" type="xs:string" minOccurs="0"/>
      <xs:element name="colour" type="xs:string" minOccurs="0"/>
      <xs:element name="id" type="xs:int"/>
      <xs:element name="weight" type="xs:float"/>
    </xs:sequence>
  </xs:complexType>
  <xs:complexType name="potatoArray" final="#all">
    <xs:sequence>
      <xs:element name="item" type="tns:potato" minOccurs="0" maxOccurs="unbounded" nillable="true"/>
    </xs:sequence>
  </xs:complexType>
</xs:schema>]]></con:content><con:type>http://www.w3.org/2001/XMLSchema</con:type></con:part></con:definitionCache><con:endpoints><con:endpoint>http://localhost:8000/services/Potato</con:endpoint></con:endpoints><con:operation id="64b32947-6642-427e-8cdd-8fd622fdd2ca" isOneWay="false" action="" name="addPotato" bindingOperationName="addPotato" type="Request-Response" inputName="" receivesAttachments="false" sendsAttachments="false" anonymous="optional"><con:settings/><con:call id="e3ec81b6-3469-440f-b603-5a950125c5de" name="Request 1"><con:settings/><con:encoding>UTF-8</con:encoding><con:endpoint>http://localhost:8000/services/Potato</con:endpoint><con:request><![CDATA[<soapenv:Envelope xmlns:soapenv="http://schemas.xmlsoap.org/soap/envelope/" xmlns:ser="http://service.soap.william.me/">
   <soapenv:Header/>
   <soapenv:Body>
      <ser:addPotato>
         <arg0>
            <!--Optional:-->
            <breed>?</breed>
            <!--Optional:-->
            <colour>?</colour>
            <id>?</id>
            <weight>?</weight>
         </arg0>
      </ser:addPotato>
   </soapenv:Body>
</soapenv:Envelope>]]></con:request><con:credentials><con:authType>No Authorization</con:authType></con:credentials><con:jmsConfig JMSDeliveryMode="PERSISTENT"/><con:jmsPropertyConfig/><con:wsaConfig mustUnderstand="NONE" version="200508" action="http://service.soap.william.me/PotatoService/addPotatoRequest"/><con:wsrmConfig version="1.2"/></con:call></con:operation><con:operation id="a1a09ebe-b78a-4e85-9134-5f49a0fc23e0" isOneWay="false" action="" name="deletePotato" bindingOperationName="deletePotato" type="Request-Response" inputName="" receivesAttachments="false" sendsAttachments="false" anonymous="optional"><con:settings/><con:call id="89343548-f17d-45dc-ad28-8822845ddb81" name="Request 1"><con:settings/><con:encoding>UTF-8</con:encoding><con:endpoint>http://localhost:8000/services/Potato</con:endpoint><con:request><![CDATA[<soapenv:Envelope xmlns:soapenv="http://schemas.xmlsoap.org/soap/envelope/" xmlns:ser="http://service.soap.william.me/">
   <soapenv:Header/>
   <soapenv:Body>
      <ser:deletePotato>
         <arg0>?</arg0>
      </ser:deletePotato>
   </soapenv:Body>
</soapenv:Envelope>]]></con:request><con:wsaConfig mustUnderstand="NONE" version="200508" action="http://service.soap.william.me/PotatoService/deletePotatoRequest"/></con:call></con:operation><con:operation id="bb9609cc-e76f-4a6f-85f7-00c695bdefe3" isOneWay="false" action="" name="getAllPotatoes" bindingOperationName="getAllPotatoes" type="Request-Response" inputName="" receivesAttachments="false" sendsAttachments="false" anonymous="optional"><con:settings/><con:call id="4216c297-0098-4f66-9d59-3eb3b9ac5039" name="Request 1"><con:settings/><con:encoding>UTF-8</con:encoding><con:endpoint>http://localhost:8000/services/Potato</con:endpoint><con:request><![CDATA[<soapenv:Envelope xmlns:soapenv="http://schemas.xmlsoap.org/soap/envelope/" xmlns:ser="http://service.soap.william.me/">
   <soapenv:Header/>
   <soapenv:Body>
      <ser:getAllPotatoes/>
   </soapenv:Body>
</soapenv:Envelope>]]></con:request><con:credentials><con:authType>No Authorization</con:authType></con:credentials><con:jmsConfig JMSDeliveryMode="PERSISTENT"/><con:jmsPropertyConfig/><con:wsaConfig mustUnderstand="NONE" version="200508" action="http://service.soap.william.me/PotatoService/getAllPotatoesRequest"/><con:wsrmConfig version="1.2"/></con:call></con:operation><con:operation id="f7f7f210-853d-4b90-b118-57b31752952b" isOneWay="false" action="" name="getPotato" bindingOperationName="getPotato" type="Request-Response" inputName="" receivesAttachments="false" sendsAttachments="false" anonymous="optional"><con:settings/><con:call id="4940978a-5a87-4924-8e0e-15f648906a84" name="Request 1"><con:settings/><con:encoding>UTF-8</con:encoding><con:endpoint>http://localhost:8000/services/Potato</con:endpoint><con:request><![CDATA[<soapenv:Envelope xmlns:soapenv="http://schemas.xmlsoap.org/soap/envelope/" xmlns:ser="http://service.soap.william.me/">
   <soapenv:Header/>
   <soapenv:Body>
      <ser:getPotato>
         <arg0>?</arg0>
      </ser:getPotato>
   </soapenv:Body>
</soapenv:Envelope>]]></con:request><con:wsaConfig mustUnderstand="NONE" version="200508" action="http://service.soap.william.me/PotatoService/getPotatoRequest"/></con:call></con:operation></con:interface><con:testSuite id="3df25c07-90a7-4570-88c4-aee924c29745" name="End To End"><con:settings/><con:runType>SEQUENTIAL</con:runType><con:testCase id="5b449413-3ac7-467c-a69c-bd1b4ad30323" failOnError="false" failTestCaseOnErrors="true" keepSession="false" maxResults="0" name="End To End" searchProperties="true" timeout="0" wsrmEnabled="false" wsrmVersion="1.0" wsrmAckTo="" amfAuthorisation="false" amfEndpoint="" amfLogin="" amfPassword=""><con:settings/><con:testStep type="request" name="Add Potato" id="8f8395e7-a089-4859-bfa1-1b3b1d189dfd"><con:settings/><con:config xsi:type="con:RequestStep" xmlns:xsi="http://www.w3.org/2001/XMLSchema-instance"><con:interface>PotatoServiceImplPortBinding</con:interface><con:operation>addPotato</con:operation><con:request name="Add Potato" id="7bae3c94-6e5b-4256-9822-5a24c491b1d6"><con:settings><con:setting id="com.eviware.soapui.impl.wsdl.WsdlRequest@request-headers">&lt;xml-fragment/></con:setting></con:settings><con:encoding>UTF-8</con:encoding><con:endpoint>http://localhost:8000/services/Potato</con:endpoint><con:request><![CDATA[<soapenv:Envelope xmlns:soapenv="http://schemas.xmlsoap.org/soap/envelope/" xmlns:ser="http://service.soap.william.me/">
   <soapenv:Header/>
   <soapenv:Body>
      <ser:addPotato>
         <arg0>
            <id>${#TestCase#id}</id>
            <weight>${#TestCase#weight}</weight>
            <breed>${#TestCase#breed}</breed>
            <colour>${#TestCase#colour}</colour>
         </arg0>
      </ser:addPotato>
   </soapenv:Body>
</soapenv:Envelope>]]></con:request><con:assertion type="SOAP Response" id="16022a6b-841e-4f71-b075-ed552c9b5cf5"/><con:assertion type="XPath Match" id="76a5c9f6-c408-4586-bea2-de09bd054e3d" name="Return true"><con:configuration><path>declare namespace ns2='http://service.soap.william.me/';
declare namespace S='http://schemas.xmlsoap.org/soap/envelope/';

/S:Envelope/S:Body/ns2:addPotatoResponse/return</path><content>true</content><allowWildcards>false</allowWildcards><ignoreNamspaceDifferences>false</ignoreNamspaceDifferences><ignoreComments>false</ignoreComments></con:configuration></con:assertion><con:assertion type="Valid HTTP Status Codes" id="5b363e40-125b-4fd3-968f-55c7b6116738" name="Valid HTTP Status Codes"><con:configuration><codes>200</codes></con:configuration></con:assertion><con:assertion type="SOAP Fault Assertion" id="2d378538-cbc9-4758-a187-4ef24920a111" name="Not SOAP Fault"/><con:assertion type="Schema Compliance" id="a07d94fa-839d-4795-b867-656abf9cd59e" name="Schema Compliance"><con:configuration><definition/></con:configuration></con:assertion><con:credentials><con:authType>No Authorization</con:authType></con:credentials><con:jmsConfig JMSDeliveryMode="PERSISTENT"/><con:jmsPropertyConfig/><con:wsaConfig mustUnderstand="NONE" version="200508"/><con:wsrmConfig version="1.2"/></con:request></con:config></con:testStep><con:testStep type="request" name="Get Potato" id="75dbd6ca-1ff3-4d4a-b944-ebfd63532678"><con:settings/><con:config xsi:type="con:RequestStep" xmlns:xsi="http://www.w3.org/2001/XMLSchema-instance"><con:interface>PotatoServiceImplPortBinding</con:interface><con:operation>getPotato</con:operation><con:request name="Get Potato" id="bc89449b-4935-48a1-ba0b-e7970c3099ab"><con:settings><con:setting id="com.eviware.soapui.impl.wsdl.WsdlRequest@request-headers">&lt;xml-fragment/></con:setting></con:settings><con:encoding>UTF-8</con:encoding><con:endpoint>http://localhost:8000/services/Potato</con:endpoint><con:request><![CDATA[<soapenv:Envelope xmlns:soapenv="http://schemas.xmlsoap.org/soap/envelope/" xmlns:ser="http://service.soap.william.me/">
   <soapenv:Header/>
   <soapenv:Body>
      <ser:getPotato>
         <arg0>0</arg0>
      </ser:getPotato>
   </soapenv:Body>
</soapenv:Envelope>]]></con:request><con:assertion type="SOAP Response" id="cb6ce75c-a804-437b-a49e-adfe8c58ceec"/><con:assertion type="Schema Compliance" id="8a8da567-ba8d-4222-82af-b10d5b8fdb72"><con:configuration/></con:assertion><con:assertion type="SOAP Fault Assertion" id="e92a3535-d1d9-4249-bd35-c5bb393bdc75"/><con:assertion type="XPath Match" id="31c88f2f-62c9-41ca-8ae8-8c591f1e3492" name="Breed matches"><con:configuration><path>//return/breed</path><content>${#TestCase#breed}</content><allowWildcards>false</allowWildcards><ignoreNamspaceDifferences>false</ignoreNamspaceDifferences><ignoreComments>false</ignoreComments></con:configuration></con:assertion><con:assertion type="XPath Match" id="31c88f2f-62c9-41ca-8ae8-8c591f1e3492" name="Colour matches"><con:configuration><path>//return/colour</path><content>${#TestCase#colour}</content><allowWildcards>false</allowWildcards><ignoreNamspaceDifferences>false</ignoreNamspaceDifferences><ignoreComments>false</ignoreComments></con:configuration></con:assertion><con:assertion type="XPath Match" id="31c88f2f-62c9-41ca-8ae8-8c591f1e3492" name="Weight matches"><con:configuration><path>//return/weight</path><content>${#TestCase#weight}</content><allowWildcards>false</allowWildcards><ignoreNamspaceDifferences>false</ignoreNamspaceDifferences><ignoreComments>false</ignoreComments></con:configuration></con:assertion><con:assertion type="XPath Match" id="31c88f2f-62c9-41ca-8ae8-8c591f1e3492" name="ID matches"><con:configuration><path>//return/id</path><content>${#TestCase#id}</content><allowWildcards>false</allowWildcards><ignoreNamspaceDifferences>false</ignoreNamspaceDifferences><ignoreComments>false</ignoreComments></con:configuration></con:assertion><con:credentials><con:authType>No Authorization</con:authType></con:credentials><con:jmsConfig JMSDeliveryMode="PERSISTENT"/><con:jmsPropertyConfig/><con:wsaConfig mustUnderstand="NONE" version="200508"/><con:wsrmConfig version="1.2"/></con:request></con:config></con:testStep><con:testStep type="request" name="Get All Potatoes" id="a2fc3bbe-e88f-4186-98a6-07ccfd1b7908"><con:settings/><con:config xsi:type="con:RequestStep" xmlns:xsi="http://www.w3.org/2001/XMLSchema-instance"><con:interface>PotatoServiceImplPortBinding</con:interface><con:operation>getPotato</con:operation><con:request name="Get All Potatoes" id="bc89449b-4935-48a1-ba0b-e7970c3099ab"><con:settings><con:setting id="com.eviware.soapui.impl.wsdl.WsdlRequest@request-headers">&lt;xml-fragment/></con:setting></con:settings><con:encoding>UTF-8</con:encoding><con:endpoint>http://localhost:8000/services/Potato</con:endpoint><con:request><![CDATA[<soapenv:Envelope xmlns:soapenv="http://schemas.xmlsoap.org/soap/envelope/" xmlns:ser="http://service.soap.william.me/">
   <soapenv:Header/>
   <soapenv:Body>
      <ser:getAllPotatoes/>
   </soapenv:Body>
</soapenv:Envelope>]]></con:request><con:assertion type="SOAP Response" id="cb6ce75c-a804-437b-a49e-adfe8c58ceec"/><con:assertion type="SOAP Fault Assertion" id="e92a3535-d1d9-4249-bd35-c5bb393bdc75"/><con:assertion type="XPath Match" id="31c88f2f-62c9-41ca-8ae8-8c591f1e3492" name="Breed matches"><con:configuration><path>//item/breed</path><content>${#TestCase#breed}</content><allowWildcards>false</allowWildcards><ignoreNamspaceDifferences>false</ignoreNamspaceDifferences><ignoreComments>false</ignoreComments></con:configuration></con:assertion><con:assertion type="XPath Match" id="31c88f2f-62c9-41ca-8ae8-8c591f1e3492" name="Colour matches"><con:configuration><path>//item/colour</path><content>${#TestCase#colour}</content><allowWildcards>false</allowWildcards><ignoreNamspaceDifferences>false</ignoreNamspaceDifferences><ignoreComments>false</ignoreComments></con:configuration></con:assertion><con:assertion type="XPath Match" id="31c88f2f-62c9-41ca-8ae8-8c591f1e3492" name="Weight matches"><con:configuration><path>//item/weight</path><content>${#TestCase#weight}</content><allowWildcards>false</allowWildcards><ignoreNamspaceDifferences>false</ignoreNamspaceDifferences><ignoreComments>false</ignoreComments></con:configuration></con:assertion><con:assertion type="XPath Match" id="31c88f2f-62c9-41ca-8ae8-8c591f1e3492" name="ID matches"><con:configuration><path>//item/id</path><content>${#TestCase#id}</content><allowWildcards>false</allowWildcards><ignoreNamspaceDifferences>false</ignoreNamspaceDifferences><ignoreComments>false</ignoreComments></con:configuration></con:assertion><con:credentials><con:authType>No Authorization</con:authType></con:credentials><con:jmsConfig JMSDeliveryMode="PERSISTENT"/><con:jmsPropertyConfig/><con:wsaConfig mustUnderstand="NONE" version="200508"/><con:wsrmConfig version="1.2"/></con:request></con:config></con:testStep><con:testStep type="request" name="Delete Potato" id="f06dbd30-08f0-494d-8e4c-4eef8d0c21c5"><con:settings/><con:config xsi:type="con:RequestStep" xmlns:xsi="http://www.w3.org/2001/XMLSchema-instance"><con:interface>PotatoServiceImplPortBinding</con:interface><con:operation>deletePotato</con:operation><con:request name="Delete Potato" id="717b279c-d8d9-4c66-8b73-89a6e104d9c5"><con:settings><con:setting id="com.eviware.soapui.impl.wsdl.WsdlRequest@request-headers">&lt;xml-fragment/></con:setting></con:settings><con:encoding>UTF-8</con:encoding><con:endpoint>http://localhost:8000/services/Potato</con:endpoint><con:request><![CDATA[<soapenv:Envelope xmlns:soapenv="http://schemas.xmlsoap.org/soap/envelope/" xmlns:ser="http://service.soap.william.me/">
   <soapenv:Header/>
   <soapenv:Body>
      <ser:deletePotato>
         <arg0>${#TestCase#id}</arg0>
      </ser:deletePotato>
   </soapenv:Body>
</soapenv:Envelope>]]></con:request><con:assertion type="SOAP Response" id="be0f743d-ec75-4fba-925a-5a5e058ef610"/><con:assertion type="Schema Compliance" id="c946045b-41d5-4b76-9a2d-f832d7e88a33"><con:configuration/></con:assertion><con:assertion type="SOAP Fault Assertion" id="dc0c4c1f-37f0-4e7d-9ead-bbd8dae64ec3"/><con:assertion type="XPath Match" id="dcaeea5d-90fd-48f3-b474-c1a12b9f9a98" name="Return true"><con:configuration><path>//return</path><content>true</content><allowWildcards>false</allowWildcards><ignoreNamspaceDifferences>false</ignoreNamspaceDifferences><ignoreComments>false</ignoreComments></con:configuration></con:assertion><con:credentials><con:authType>No Authorization</con:authType></con:credentials><con:jmsConfig JMSDeliveryMode="PERSISTENT"/><con:jmsPropertyConfig/><con:wsaConfig mustUnderstand="NONE" version="200508"/><con:wsrmConfig version="1.2"/></con:request></con:config></con:testStep><con:properties><con:property><con:name>id</con:name><con:value>0</con:value></con:property><con:property><con:name>weight</con:name><con:value>1.0</con:value></con:property><con:property><con:name>breed</con:name><con:value>rooster</con:value></con:property><con:property><con:name>colour</con:name><con:value>red</con:value></con:property></con:properties></con:testCase><con:properties/></con:testSuite><con:properties/><con:wssContainer/><con:oAuth2ProfileContainer/><con:oAuth1ProfileContainer/><con:sensitiveInformation/></con:soapui-project>